Metadata-Version: 1.1
Name: schmecko
Version: 0.0.2
Summary: Debugging http server
Home-page: http://github.com/rmfitzpatrick/schmecko
Author: Ryan Fitzpatrick
Author-email: rmfitzpatrick@gmail.com
License: MIT
Download-URL: http://github.com/rmfitzpatrick/schmecko/tarball/master
Platform: UNKNOWN
Classifier: Development Status :: 4 - Beta
Classifier: Intended Audience :: Developers
Classifier: Natural Language :: English
Classifier: License :: OSI Approved :: Apache Software License
Classifier: Programming Language :: Python
Classifier: Programming Language :: Python :: 2
Classifier: Programming Language :: Python :: 2.7
Classifier: Programming Language :: Python :: 3
Classifier: Programming Language :: Python :: 3.4
Classifier: Programming Language :: Python :: 3.5
Classifier: Programming Language :: Python :: 3.6
Classifier: Programming Language :: Python :: 3.7
